simpyl/__init__.py
simpyl/reader.py
simpyl/datafiles/sample.json
simpyl/datafiles/sample.yaml
simpyl-0.0.1a3.dist-info/METADATA
simpyl-0.0.1a3.dist-info/WHEEL
simpyl-0.0.1a3.dist-info/top_level.txt
simpyl-0.0.1a3.dist-info/RECORD
